audit_logger/__init__.py
audit_logger/apps.py
audit_logger/helpers.py
audit_logger/logger.py
audit_logger/middlewares.py
audit_logger/kafka/__init__.py
audit_logger/kafka/async_producer.py
audit_logger/kafka/local_logger.py
audit_logger/kafka/main.py
audit_logger/kafka/topic_manager.py
unemi_audi_kafka-1.2.6.dist-info/LICENSE
unemi_audi_kafka-1.2.6.dist-info/METADATA
unemi_audi_kafka-1.2.6.dist-info/WHEEL
unemi_audi_kafka-1.2.6.dist-info/top_level.txt
unemi_audi_kafka-1.2.6.dist-info/RECORD
