Metadata-Version: 2.1
Name: unemi-audi-kafka
Version: 1.2.6
Summary: Una aplicación reutilizable de Django para auditar modelos automáticamente con integración con Kafka.
Home-page: https://github.com/marcosdaniel2002/django-audit-kafkalogger
Author: Marcos Daniel
Author-email: mteranc@unemi.edu.ec
License: MIT
Platform: UNKNOWN
Classifier: Framework :: Django
Classifier: Programming Language :: Python
Classifier: Programming Language :: Python :: 3
Classifier: License :: OSI Approved :: MIT License
Classifier: Operating System :: OS Independent
Requires-Python: >=3.6
License-File: LICENSE
Requires-Dist: Django>=3.1
Requires-Dist: confluent-kafka>=1.7.0
Requires-Dist: aiokafka>=0.11.0
